Metadata-Version: 2.4
Name: x_4357_make_progress_board_x
Version: 0.20.17
Summary: PySide6 progress board launcher.
Author-email: "RRGM (Software Tech Lead, Primus Pilus Night Watch AI Corp.)" <foo@bar.com>
Requires-Python: >=3.8
Requires-Dist: PySide6<7,>=6.7
